<?xml version="1.0"?>
<countries>
    <country>
        <code>pl</code>
        <lang>pl</lang>
        <name>hm.country.pl</name>
        <continent>hm.continent.europe</continent>
        <conversion_data>
            <connversion_item>
                <id>4</id>
                <name>hm.combo.conversion.watts</name>
                <unit_name>hm.combo.conversion.unit.watts</unit_name>
            </connversion_item>
            <connversion_item>
                <id>3</id>
                <name>hm.combo.conversion.kwh_year</name>
                <unit_name>hm.combo.conversion.unit.kwh_year</unit_name>
            </connversion_item>
            <connversion_item>
                <id>5</id>
                <name>hm.combo.conversion.gj_year</name>
                <unit_name>hm.combo.conversion.unit.gj_year</unit_name>
            </connversion_item>
            <connversion_item>
                <id>2</id>
                <name>hm.combo.conversion.kwh_month</name>
                <unit_name>hm.combo.conversion.unit.khw_month</unit_name>
            </connversion_item>
            <connversion_item>
                <id>6</id>
                <name>hm.combo.conversion.gj_month</name>
                <unit_name>hm.combo.conversion.unit.gj_month</unit_name>
            </connversion_item>
            <connversion_item>
                <id>6</id>
                <name>hm.combo.conversion.co2_year</name>
                <unit_name>hm.combo.conversion.unit.co2_year</unit_name>
            </connversion_item>
            <connversion_item default="true">
                <id>1</id>
                <name>hm.combo.conversion.year_cost</name>
                <unit_name>hm.combo.conversion.unit.year_cost</unit_name>
            </connversion_item>
            <connversion_item>
                <id>0</id>
                <name>hm.combo.conversion.month_cost</name>
                <unit_name>hm.combo.conversion.unit.month_cost</unit_name>
            </connversion_item>
        </conversion_data>
        <environmental_data>
            <temperatures>
                <value>-2</value>
                <value>-1</value>
                <value>3</value>
                <value>7</value>
                <value>13</value>
                <value>17</value>
                <value>18</value>
                <value>17</value>
                <value>13</value>
                <value>9</value>
                <value>3</value>
                <value>-1</value>
            </temperatures>
            <insolationS>
                <value>31</value>
                <value>51</value>
                <value>77</value>
                <value>80</value>
                <value>88</value>
                <value>82</value>
                <value>88</value>
                <value>90</value>
                <value>75</value>
                <value>62</value>
                <value>35</value>
                <value>23</value>
            </insolationS>
            <insolationWE>
                <value>17</value>
                <value>31</value>
                <value>55</value>
                <value>69</value>
                <value>89</value>
                <value>90</value>
                <value>89</value>
                <value>80</value>
                <value>53</value>
                <value>34</value>
                <value>16</value>
                <value>10</value>
            </insolationWE>
            <insolationN>
                <value>13</value>
                <value>23</value>
                <value>39</value>
                <value>46</value>
                <value>63</value>
                <value>68</value>
                <value>68</value>
                <value>52</value>
                <value>35</value>
                <value>21</value>
                <value>11</value>
                <value>8</value>
            </insolationN>
            <ground_insolation45>
                <value>28</value>
                <value>48</value>
                <value>81</value>
                <value>107</value>
                <value>136</value>
                <value>132</value>
                <value>133</value>
                <value>126</value>
                <value>94</value>
                <value>65</value>
                <value>30</value>
                <value>19</value>
            </ground_insolation45>
            <ground_temperatures>
                <value>1</value>
                <value>1</value>
                <value>0</value>
                <value>3</value>
                <value>8</value>
                <value>14</value>
                <value>16</value>
                <value>17</value>
                <value>14</value>
                <value>10</value>
                <value>6</value>
                <value>4</value>
            </ground_temperatures>
        </environmental_data>
        <building_age_list>
            <building_age default="true">
                <label>hm.combo.building.age.before84</label>
                <from>-1</from>
                <to>1984</to>
                <u_wall>1.4</u_wall>
                <u_roof>0.9</u_roof>
                <u_floor>0.5</u_floor>
                <u_windows>2.6</u_windows>
            </building_age>
            <building_age>
                <from>1984</from>
                <to>1993</to>
                <u_wall>0.75</u_wall>
                <u_roof>0.5</u_roof>
                <u_floor>0.5</u_floor>
                <u_windows>2.6</u_windows>
            </building_age>
            <building_age>
                <from>1993</from>
                <to>2004</to>
                <u_wall>0.65</u_wall>
                <u_roof>0.3</u_roof>
                <u_floor>0.5</u_floor>
                <u_windows>2</u_windows>
            </building_age>
            <building_age>
                <from>2004</from>
                <to>2010</to>
                <u_wall>0.45</u_wall>
                <u_roof>0.3</u_roof>
                <u_floor>0.5</u_floor>
                <u_windows>1.6</u_windows>
            </building_age>
            <building_age>
                <from>2010</from>
                <to>2013</to>
                <u_wall>0.35</u_wall>
                <u_roof>0.25</u_roof>
                <u_floor>0.5</u_floor>
                <u_windows>1.4</u_windows>
            </building_age>
        </building_age_list>
        <house_data>
            <default_house_type>1</default_house_type>
            <default_surface>120</default_surface>
            <default_floor_count>1</default_floor_count>
            <default_floor_height>2.7</default_floor_height>
            <default_temperature>20</default_temperature>
        </house_data>
        <house_heating>
            <heating_list>
                <heating_source_type default="true" detached="true" multifamily="false">
                    <id>1</id>
                    <name>hm.combo.heating.type.biomass.pellets</name>
                    <efficiency>75</efficiency>
                    <price_kwh>0.22</price_kwh>
                    <emission_kwh>0.03</emission_kwh>
                    <final_primary_coefficient>0.2</final_primary_coefficient>
                </heating_source_type>
                <heating_source_type detached="true" multifamily="false">
                    <id>2</id>
                    <name>hm.combo.heating.type.biomass.wood</name>
                    <efficiency>70</efficiency>
                    <price_kwh>0.12</price_kwh>
                    <emission_kwh>0.03</emission_kwh>
                    <final_primary_coefficient>0.2</final_primary_coefficient>
                </heating_source_type>
                <heating_source_type detached="true" multifamily="true">
                    <id>3</id>
                    <name>hm.combo.heating.type.combined_heat</name>
                    <efficiency>97</efficiency>
                    <price_kwh>0.22</price_kwh>
                    <emission_kwh>0.4</emission_kwh>
                    <final_primary_coefficient>1.3</final_primary_coefficient>
                </heating_source_type>
                <heating_source_type detached="true" multifamily="true">
                    <id>4</id>
                    <name>hm.combo.heating.type.combined_electric_heat</name>
                    <efficiency>75</efficiency>
                    <price_kwh>0.22</price_kwh>
                    <emission_kwh>0.08</emission_kwh>
                    <final_primary_coefficient>0.8</final_primary_coefficient>
                </heating_source_type>
                <heating_source_type detached="true" multifamily="false">
                    <id>5</id>
                    <name>hm.combo.heating.type.furnace</name>
                    <efficiency>40</efficiency>
                    <price_kwh>0.12</price_kwh>
                    <emission_kwh>0.38</emission_kwh>
                    <final_primary_coefficient>1.1</final_primary_coefficient>
                </heating_source_type>
                <heating_source_type detached="true" multifamily="false">
                    <id>6</id>
                    <name>hm.combo.heating.type.coal.old</name>
                    <efficiency>60</efficiency>
                    <price_kwh>0.12</price_kwh>
                    <emission_kwh>0.38</emission_kwh>
                    <final_primary_coefficient>1.1</final_primary_coefficient>
                </heating_source_type>
                <heating_source_type detached="true" multifamily="false">
                    <id>7</id>
                    <name>hm.combo.heating.type.coal.modern</name>
                    <efficiency>80</efficiency>
                    <price_kwh>0.12</price_kwh>
                    <emission_kwh>0.38</emission_kwh>
                    <final_primary_coefficient>1.1</final_primary_coefficient>
                </heating_source_type>
                <heating_source_type detached="true" multifamily="true">
                    <id>8</id>
                    <name>hm.combo.heating.type.boiler.gas_old</name>
                    <efficiency>65</efficiency>
                    <price_kwh>0.18</price_kwh>
                    <emission_kwh>0.201</emission_kwh>
                    <final_primary_coefficient>1.1</final_primary_coefficient>
                </heating_source_type>
                <heating_source_type detached="true" multifamily="true">
                    <id>9</id>
                    <name>hm.combo.heating.type.boiler.gas_modern</name>
                    <efficiency>85</efficiency>
                    <price_kwh>0.18</price_kwh>
                    <emission_kwh>0.201</emission_kwh>
                    <final_primary_coefficient>1.1</final_primary_coefficient>
                </heating_source_type>
                <heating_source_type detached="true" multifamily="true">
                    <id>10</id>
                    <name>hm.combo.heating.type.boiler.gas_condensing</name>
                    <efficiency>95</efficiency>
                    <price_kwh>0.18</price_kwh>
                    <emission_kwh>0.201</emission_kwh>
                    <final_primary_coefficient>1.1</final_primary_coefficient>
                </heating_source_type>
                <heating_source_type detached="true" multifamily="true">
                    <id>11</id>
                    <name>hm.combo.heating.type.boiler.propan_standard</name>
                    <efficiency>85</efficiency>
                    <price_kwh>0.32</price_kwh>
                    <emission_kwh>0.225</emission_kwh>
                    <final_primary_coefficient>1.1</final_primary_coefficient>
                </heating_source_type>
                <heating_source_type detached="true" multifamily="true">
                    <id>12</id>
                    <name>hm.combo.heating.type.boiler.propan_condensing</name>
                    <efficiency>95</efficiency>
                    <price_kwh>0.32</price_kwh>
                    <emission_kwh>0.225</emission_kwh>
                    <final_primary_coefficient>1.1</final_primary_coefficient>
                </heating_source_type>
                <heating_source_type detached="true" multifamily="true">
                    <id>15</id>
                    <name>hm.combo.heating.type.boiler.oil</name>
                    <efficiency>85</efficiency>
                    <price_kwh>0.4</price_kwh>
                    <emission_kwh>0.276</emission_kwh>
                    <final_primary_coefficient>1.1</final_primary_coefficient>
                </heating_source_type>
                <heating_source_type detached="true" multifamily="true">
                    <id>16</id>
                    <name>hm.combo.heating.type.electric</name>
                    <efficiency>100</efficiency>
                    <price_kwh>0.58</price_kwh>
                    <emission_kwh>0.9</emission_kwh>
                    <final_primary_coefficient>3</final_primary_coefficient>
                </heating_source_type>
                <heating_source_type detached="true" multifamily="true">
                    <id>17</id>
                    <name>hm.combo.heating.type.heat_pump</name>
                    <efficiency>350</efficiency>
                    <price_kwh>0.58</price_kwh>
                    <emission_kwh>0.9</emission_kwh>
                    <final_primary_coefficient>3</final_primary_coefficient>
                </heating_source_type>
            </heating_list>
        </house_heating>
        <warm_water>
            <heating_list>
                <heating_source_type default="true" detached="true" multifamily="false">
                    <id>1</id>
                    <name>hm.combo.heating.type.biomass.pellets</name>
                    <efficiency>75</efficiency>
                    <price_kwh>0.22</price_kwh>
                    <emission_kwh>0.03</emission_kwh>
                    <final_primary_coefficient>0.2</final_primary_coefficient>
                </heating_source_type>
                <heating_source_type detached="true" multifamily="false">
                    <id>2</id>
                    <name>hm.combo.heating.type.biomass.wood</name>
                    <efficiency>70</efficiency>
                    <price_kwh>0.12</price_kwh>
                    <emission_kwh>0.03</emission_kwh>
                    <final_primary_coefficient>0.2</final_primary_coefficient>
                </heating_source_type>
                <heating_source_type detached="true" multifamily="true">
                    <id>3</id>
                    <name>hm.combo.heating.type.combined_heat</name>
                    <efficiency>97</efficiency>
                    <price_kwh>0.22</price_kwh>
                    <emission_kwh>0.4</emission_kwh>
                    <final_primary_coefficient>1.3</final_primary_coefficient>
                </heating_source_type>
                <heating_source_type detached="true" multifamily="true">
                    <id>4</id>
                    <name>hm.combo.heating.type.combined_electric_heat</name>
                    <efficiency>75</efficiency>
                    <price_kwh>0.22</price_kwh>
                    <emission_kwh>0.08</emission_kwh>
                    <final_primary_coefficient>0.8</final_primary_coefficient>
                </heating_source_type>
                <heating_source_type detached="true" multifamily="true">
                    <id>8</id>
                    <name>hm.combo.heating.type.boiler.gas_old</name>
                    <efficiency>65</efficiency>
                    <price_kwh>0.18</price_kwh>
                    <emission_kwh>0.201</emission_kwh>
                    <final_primary_coefficient>1.1</final_primary_coefficient>
                </heating_source_type>
                <heating_source_type detached="true" multifamily="true">
                    <id>9</id>
                    <name>hm.combo.heating.type.boiler.gas_modern</name>
                    <efficiency>85</efficiency>
                    <price_kwh>0.18</price_kwh>
                    <emission_kwh>0.201</emission_kwh>
                    <final_primary_coefficient>1.1</final_primary_coefficient>
                </heating_source_type>
                <heating_source_type detached="true" multifamily="true">
                    <id>10</id>
                    <name>hm.combo.heating.type.boiler.gas_condensing</name>
                    <efficiency>95</efficiency>
                    <price_kwh>0.18</price_kwh>
                    <emission_kwh>0.201</emission_kwh>
                    <final_primary_coefficient>1.1</final_primary_coefficient>
                </heating_source_type>
                <heating_source_type detached="true" multifamily="true">
                    <id>11</id>
                    <name>hm.combo.heating.type.boiler.propan_standard</name>
                    <efficiency>85</efficiency>
                    <price_kwh>0.32</price_kwh>
                    <emission_kwh>0.225</emission_kwh>
                    <final_primary_coefficient>1.1</final_primary_coefficient>
                </heating_source_type>
                <heating_source_type detached="true" multifamily="true">
                    <id>12</id>
                    <name>hm.combo.heating.type.boiler.propan_condensing</name>
                    <efficiency>95</efficiency>
                    <price_kwh>0.32</price_kwh>
                    <emission_kwh>0.225</emission_kwh>
                    <final_primary_coefficient>1.1</final_primary_coefficient>
                </heating_source_type>

                <heating_source_type detached="true" multifamily="true">
                    <id>13</id>
                    <name>hm.combo.heating.type.heater.gas_electric</name>
                    <efficiency>90</efficiency>
                    <price_kwh>0.18</price_kwh>
                    <emission_kwh>0.9</emission_kwh>
                    <final_primary_coefficient>1.1</final_primary_coefficient>
                </heating_source_type>
                <heating_source_type detached="true" multifamily="true">
                    <id>14</id>
                    <name>hm.combo.heating.type.heater.gas_heater</name>
                    <efficiency>70</efficiency>
                    <price_kwh>0.18</price_kwh>
                    <emission_kwh>0.201</emission_kwh>
                    <final_primary_coefficient>1.1</final_primary_coefficient>
                </heating_source_type>
                <heating_source_type detached="true" multifamily="true">
                    <id>15</id>
                    <name>hm.combo.heating.type.boiler.oil</name>
                    <efficiency>85</efficiency>
                    <price_kwh>0.4</price_kwh>
                    <emission_kwh>0.276</emission_kwh>
                    <final_primary_coefficient>1.1</final_primary_coefficient>
                </heating_source_type>
                <heating_source_type detached="true" multifamily="true">
                    <id>16</id>
                    <name>hm.combo.heating.type.electric</name>
                    <efficiency>100</efficiency>
                    <price_kwh>0.58</price_kwh>
                    <emission_kwh>0.9</emission_kwh>
                    <final_primary_coefficient>3</final_primary_coefficient>
                </heating_source_type>
                <heating_source_type detached="true" multifamily="true">
                    <id>17</id>
                    <name>hm.combo.heating.type.heat_pump</name>
                    <efficiency>350</efficiency>
                    <price_kwh>0.58</price_kwh>
                    <emission_kwh>0.9</emission_kwh>
                    <final_primary_coefficient>3</final_primary_coefficient>
                </heating_source_type>
            </heating_list>
            <consumption_list>
                <consumption_item>
                    <name>hm.combo.warm_water.consumption.very_small</name>
                    <intensity>0.5</intensity>
                </consumption_item>
                <consumption_item>
                    <name>hm.combo.warm_water.consumption.small</name>
                    <intensity>0.75</intensity>
                </consumption_item>
                <consumption_item default="true">
                    <name>hm.combo.warm_water.consumption.average</name>
                    <intensity>1</intensity>
                </consumption_item>
                <consumption_item>
                    <name>hm.combo.warm_water.consumption.big</name>
                    <intensity>1.5</intensity>
                </consumption_item>
                <consumption_item>
                    <name>hm.combo.warm_water.consumption.very_big</name>
                    <intensity>2.0</intensity>
                </consumption_item>
            </consumption_list>
            <detached_distribution_list>
                <distribution_item default="true">
                    <id>1</id>
                    <efficiency>0.95</efficiency>
                    <name>hm.combo.warm_water.distribution.pipes.well_isolated</name>
                </distribution_item>
                <distribution_item>
                    <id>2</id>
                    <efficiency>0.85</efficiency>
                    <name>hm.combo.warm_water.distribution.pipes.plastic_isolated</name>
                </distribution_item>
                <distribution_item>
                    <id>3</id>
                    <efficiency>0.60</efficiency>
                    <name>hm.combo.warm_water.distribution.pipes.poor_isolated</name>
                </distribution_item>
            </detached_distribution_list>
            <multi_family_distribution_list>
                <distribution_item default="true">
                    <id>4</id>
                    <efficiency>0.70</efficiency>
                    <name>hm.combo.warm_water.distribution.pipes.well_isolated_automatic</name>
                </distribution_item>
                <distribution_item>
                    <id>5</id>
                    <efficiency>0.50</efficiency>
                    <name>hm.combo.warm_water.distribution.pipes.none</name>
                </distribution_item>
            </multi_family_distribution_list>
            <storage_list>
                <storage_item>
                    <id>1</id>
                    <name>hm.combo.warm_water.storage.heat_node</name>
                    <efficiency>1.0</efficiency>
                </storage_item>
                <storage_item>
                    <id>2</id>
                    <name>hm.combo.warm_water.storage.modern</name>
                    <efficiency>0.85</efficiency>
                </storage_item>
                <storage_item>
                    <id>3</id>
                    <name>hm.combo.warm_water.storage.standard_80_90</name>
                    <efficiency>0.65</efficiency>
                </storage_item>
                <storage_item>
                    <id>4</id>
                    <name>hm.combo.warm_water.storage.old</name>
                    <efficiency>0.50</efficiency>
                </storage_item>
            </storage_list>
        </warm_water>
        <solar_collectors>
            <solar_collector>
                <id>1</id>
                <name>hm.combo.solar_collector.none</name>
                <efficiency>0</efficiency>
                <unitSurface>1</unitSurface>
                <person>0</person>
            </solar_collector>
            <solar_collector>
                <id>1</id>
                <name>hm.combo.solar_collector.flat</name>
                <efficiency>0.3</efficiency>
                <unitSurface>1.0</unitSurface>
                <person>1</person>
            </solar_collector>
            <solar_collector>
                <id>1</id>
                <name>hm.combo.solar_collector.vacuum</name>
                <efficiency>0.5</efficiency>
                <unitSurface>2.0</unitSurface>
                <person>2</person>
            </solar_collector>
        </solar_collectors>

        <wall_insulation_list>
            <insulation_item>
                <id>2</id>
                <name>hm.combo.insulation.none</name>
                <from_width>0</from_width>
                <to_width>1</to_width>
                <default_width>0</default_width>
            </insulation_item>
            <insulation_item>
                <id>3</id>
                <name>hm.combo.insulation.very_weak</name>
                <from_width>1</from_width>
                <to_width>3</to_width>
                <default_width>2</default_width>
            </insulation_item>
            <insulation_item>
                <id>4</id>
                <name>hm.combo.insulation.weak</name>
                <from_width>3</from_width>
                <to_width>6</to_width>
                <default_width>4</default_width>
            </insulation_item>
            <insulation_item>
                <id>5</id>
                <name>hm.combo.insulation.average</name>
                <from_width>6</from_width>
                <to_width>12</to_width>
                <default_width>8</default_width>
            </insulation_item>
            <insulation_item>
                <id>6</id>
                <name>hm.combo.insulation.good</name>
                <from_width>12</from_width>
                <to_width>20</to_width>
                <default_width>15</default_width>
            </insulation_item>
            <insulation_item>
                <id>7</id>
                <name>hm.combo.insulation.very_good</name>
                <from_width>20</from_width>
                <to_width>35</to_width>
                <default_width>25</default_width>
            </insulation_item>
            <insulation_item>
                <id>8</id>
                <name>hm.combo.insulation.excellent</name>
                <from_width>35</from_width>
                <to_width>1000</to_width>
                <default_width>40</default_width>
            </insulation_item>
        </wall_insulation_list>
        <roof_insulation_list>
            <insulation_item>
                <id>2</id>
                <name>hm.combo.insulation.none</name>
                <from_width>0</from_width>
                <to_width>1</to_width>
                <default_width>0</default_width>
            </insulation_item>
            <insulation_item>
                <id>3</id>
                <name>hm.combo.insulation.very_weak</name>
                <from_width>1</from_width>
                <to_width>3</to_width>
                <default_width>2</default_width>
            </insulation_item>
            <insulation_item>
                <id>4</id>
                <name>hm.combo.insulation.weak</name>
                <from_width>3</from_width>
                <to_width>6</to_width>
                <default_width>4</default_width>
            </insulation_item>
            <insulation_item>
                <id>5</id>
                <name>hm.combo.insulation.average</name>
                <from_width>6</from_width>
                <to_width>12</to_width>
                <default_width>8</default_width>
            </insulation_item>
            <insulation_item>
                <id>6</id>
                <name>hm.combo.insulation.good</name>
                <from_width>12</from_width>
                <to_width>20</to_width>
                <default_width>15</default_width>
            </insulation_item>
            <insulation_item>
                <id>7</id>
                <name>hm.combo.insulation.very_good</name>
                <from_width>20</from_width>
                <to_width>35</to_width>
                <default_width>25</default_width>
            </insulation_item>
            <insulation_item>
                <id>8</id>
                <name>hm.combo.insulation.excellent</name>
                <from_width>35</from_width>
                <to_width>1000</to_width>
                <default_width>40</default_width>
            </insulation_item>
        </roof_insulation_list>
        <floor_insulation_list>
            <insulation_item>
                <id>2</id>
                <name>hm.combo.insulation.none</name>
                <from_width>0</from_width>
                <to_width>1</to_width>
                <default_width>0</default_width>
            </insulation_item>
            <insulation_item>
                <id>3</id>
                <name>hm.combo.insulation.very_weak</name>
                <from_width>1</from_width>
                <to_width>3</to_width>
                <default_width>2</default_width>
            </insulation_item>
            <insulation_item>
                <id>4</id>
                <name>hm.combo.insulation.weak</name>
                <from_width>3</from_width>
                <to_width>6</to_width>
                <default_width>4</default_width>
            </insulation_item>
            <insulation_item>
                <id>5</id>
                <name>hm.combo.insulation.average</name>
                <from_width>6</from_width>
                <to_width>12</to_width>
                <default_width>8</default_width>
            </insulation_item>
            <insulation_item>
                <id>6</id>
                <name>hm.combo.insulation.good</name>
                <from_width>12</from_width>
                <to_width>20</to_width>
                <default_width>15</default_width>
            </insulation_item>
            <insulation_item>
                <id>7</id>
                <name>hm.combo.insulation.very_good</name>
                <from_width>20</from_width>
                <to_width>35</to_width>
                <default_width>25</default_width>
            </insulation_item>
            <insulation_item>
                <id>8</id>
                <name>hm.combo.insulation.excellent</name>
                <from_width>35</from_width>
                <to_width>1000</to_width>
                <default_width>40</default_width>
            </insulation_item>
        </floor_insulation_list>
        <doors>
            <door>
                <id>1</id>
                <name>hm.combo.door.non_energy_saving</name>
                <u>3.4</u>
            </door>
            <door>
                <id>2</id>
                <name>hm.combo.door.standard</name>
                <u>2.6</u>
            </door>
            <door>
                <id>3</id>
                <name>hm.combo.door.energy_saving</name>
                <u>1.4</u>
            </door>
            <door>
                <id>4</id>
                <name>hm.combo.door.super_energy_saving</name>
                <u>0.8</u>
            </door>
        </doors>
        <foundations>
            <foundation>
                <id>1</id>
                <name>hm.combo.foundations.standard</name>
            </foundation>
            <foundation>
                <id>2</id>
                <name>hm.combo.foundations.slab</name>
            </foundation>
        </foundations>
        <windows>
            <window>
                <id>1</id>
                <name>hm.combo.window.one_pane</name>
                <u>5.2</u>
                <gain>0.85</gain>
            </window>
            <window>
                <id>2</id>
                <name>hm.combo.window.two_pane_old</name>
                <u>2.6</u>
                <gain>0.75</gain>
            </window>
            <window>
                <id>3</id>
                <name>hm.combo.window.two_pane_new</name>
                <u>1.4</u>
                <gain>0.6</gain>
            </window>
            <window>
                <id>4</id>
                <name>hm.combo.window.three_pane</name>
                <u>0.9</u>
                <gain>0.55</gain>
            </window>
            <window>
                <id>5</id>
                <name>hm.combo.window.three_pane_special</name>
                <u>0.7</u>
                <gain>0.62</gain>
            </window>
        </windows>

        <air_tightness_list>
            <air_tightness>
                <id>1</id>
                <name>hm.combo.air_tightness.very_loose</name>
                <coefficient>10</coefficient>
            </air_tightness>
            <air_tightness>
                <id>2</id>
                <name>hm.combo.air_tightness.loose</name>
                <coefficient>7</coefficient>
            </air_tightness>
            <air_tightness>
                <id>3</id>
                <name>hm.combo.air_tightness.standard_new</name>
                <coefficient>5</coefficient>
            </air_tightness>
            <air_tightness>
                <id>4</id>
                <name>hm.combo.air_tightness.tight_no_recuperator</name>
                <coefficient>3</coefficient>
            </air_tightness>
            <air_tightness>
                <id>5</id>
                <name>hm.combo.air_tightness.tight_recuperator</name>
                <coefficient>1.5</coefficient>
            </air_tightness>
            <air_tightness>
                <id>5</id>
                <name>hm.combo.air_tightness.passive</name>
                <coefficient>0.6</coefficient>
            </air_tightness>
        </air_tightness_list>
        <ventilattion_list>
            <ventilation>
                <id>1</id>
                <name>hm.combo.ventilation.gravitational</name>
                <type>gravitational</type>
                <efficiency>0</efficiency>
            </ventilation>
            <ventilation>
                <id>1</id>
                <name>hm.combo.ventilation.mechanical_60</name>
                <type>gravitational</type>
                <efficiency>60</efficiency>
            </ventilation>
            <ventilation>
                <id>1</id>
                <name>hm.combo.ventilation.mechanical_75</name>
                <type>gravitational</type>
                <efficiency>75</efficiency>
            </ventilation>
            <ventilation>
                <id>1</id>
                <name>hm.combo.ventilation.mechanical_85</name>
                <type>gravitational</type>
                <efficiency>85</efficiency>
            </ventilation>
        </ventilattion_list>
        <ventilation_freq_list>
            <ventilation_freq>
                <id>1</id>
                <name>hm.combo.vent_freq.summer_only</name>
                <coefficient>1</coefficient>
            </ventilation_freq>
            <ventilation_freq>
                <id>2</id>
                <name>hm.combo.vent_freq.sporadically</name>
                <coefficient>0.5</coefficient>
            </ventilation_freq>
            <ventilation_freq>
                <id>3</id>
                <name>hm.combo.vent_freq.often</name>
                <coefficient>1.2</coefficient>
            </ventilation_freq>
            <ventilation_freq>
                <id>4</id>
                <name>hm.combo.vent_freq.very_often</name>
                <coefficient>2</coefficient>
            </ventilation_freq>
            <ventilation_freq>
                <id>5</id>
                <name>hm.combo.vent_freq.non_stop</name>
                <coefficient>3</coefficient>
            </ventilation_freq>
        </ventilation_freq_list>
    </country>



</countries>

